xeger/__init__.py
xeger/xeger.py
xeger/tests/__init__.py
xeger/tests/test_xeger.py
xeger-0.4.0.dist-info/LICENSE.txt
xeger-0.4.0.dist-info/METADATA
xeger-0.4.0.dist-info/WHEEL
xeger-0.4.0.dist-info/top_level.txt
xeger-0.4.0.dist-info/RECORD
